cppyy_backend/LICENSE
cppyy_backend/__init__.py
cppyy_backend/_cling_config.py
cppyy_backend/_cppyy_generator.py
cppyy_backend/_genreflex.py
cppyy_backend/_get_cppflags.py
cppyy_backend/_rootcling.py
cppyy_backend/_version.py
cppyy_backend/bindings_utils.py
cppyy_backend/loader.py
cppyy_backend/bin/genreflex
cppyy_backend/bin/rmkdepend
cppyy_backend/bin/root-config
cppyy_backend/bin/rootcint
cppyy_backend/bin/rootcling
cppyy_backend/bin/thisroot.csh
cppyy_backend/bin/thisroot.sh
cppyy_backend/cmake/FindCppyy.cmake
cppyy_backend/cmake/FindLibClang.cmake
cppyy_backend/cmake/ROOTConfig-targets-relwithdebinfo.cmake
cppyy_backend/cmake/ROOTConfig-targets.cmake
cppyy_backend/cmake/ROOTConfig-version.cmake
cppyy_backend/cmake/ROOTConfig.cmake
cppyy_backend/cmake/ROOTUseFile.cmake
cppyy_backend/cmake/RootMacros.cmake
cppyy_backend/config/Makefile.comp
cppyy_backend/config/Makefile.config
cppyy_backend/etc/Makefile.arch
cppyy_backend/etc/class.rules
cppyy_backend/etc/gdb-backtrace.sh
cppyy_backend/etc/helgrind-root.supp
cppyy_backend/etc/system.rootauthrc
cppyy_backend/etc/system.rootrc
cppyy_backend/etc/valgrind-root-python.supp
cppyy_backend/etc/valgrind-root.supp
cppyy_backend/etc/cling/cuda.modulemap
cppyy_backend/etc/cling/libc.modulemap
cppyy_backend/etc/cling/module.modulemap
cppyy_backend/etc/cling/std.modulemap
cppyy_backend/etc/cling/Interpreter/DynamicExprInfo.h
cppyy_backend/etc/cling/Interpreter/DynamicLookupLifetimeHandler.h
cppyy_backend/etc/cling/Interpreter/DynamicLookupRuntimeUniverse.h
cppyy_backend/etc/cling/Interpreter/Exception.h
cppyy_backend/etc/cling/Interpreter/RuntimeOptions.h
cppyy_backend/etc/cling/Interpreter/RuntimePrintValue.h
cppyy_backend/etc/cling/Interpreter/RuntimeUniverse.h
cppyy_backend/etc/cling/Interpreter/Value.h
cppyy_backend/etc/cling/Interpreter/Visibility.h
cppyy_backend/etc/cling/cint/multimap
cppyy_backend/etc/cling/cint/multiset
cppyy_backend/etc/cling/lib/clang/16/include/__clang_cuda_builtin_vars.h
cppyy_cling-6.32.8.dist-info/LICENSE.txt
cppyy_cling-6.32.8.dist-info/METADATA
cppyy_cling-6.32.8.dist-info/WHEEL
cppyy_cling-6.32.8.dist-info/entry_points.txt
cppyy_cling-6.32.8.dist-info/top_level.txt
cppyy_cling-6.32.8.dist-info/RECORD
