Metadata-Version: 2.1
Name: cppyy-cling
Version: 6.32.8
Summary: Re-packaged Cling, as backend for cppyy
Home-page: https://root.cern.ch/cling
Maintainer: Wim Lavrijsen
Maintainer-email: WLavrijsen@lbl.gov
License: LLVM: UoI-NCSA; ROOT: LGPL 2.1
Keywords: interpreter development
Platform: UNKNOWN
Classifier: Development Status :: 6 - Mature
Classifier: Intended Audience :: Developers
Classifier: Intended Audience :: Science/Research
Classifier: Topic :: Software Development
Classifier: Topic :: Software Development :: Interpreters
Classifier: License :: OSI Approved :: University of Illinois/NCSA Open Source License
Classifier: License :: OSI Approved :: GNU Lesser General Public License v2 or later (LGPLv2+)
Classifier: Operating System :: POSIX
Classifier: Operating System :: POSIX :: Linux
Classifier: Operating System :: MacOS :: MacOS X
Classifier: Programming Language :: Python :: 2
Classifier: Programming Language :: Python :: 2.7
Classifier: Programming Language :: C
Classifier: Programming Language :: C++
Classifier: Natural Language :: English
License-File: LICENSE.txt
